rpcx/__init__.py
rpcx/client.py
rpcx/message.py
rpcx/py.typed
rpcx/server.py
rpcx-0.4.0.dist-info/METADATA
rpcx-0.4.0.dist-info/WHEEL
rpcx-0.4.0.dist-info/licenses/LICENSE
rpcx-0.4.0.dist-info/RECORD
