Metadata-Version: 2.4
Name: rpcx
Version: 0.4.0
Summary: Asynchronous RPC client/server with streaming support
License: MIT
License-File: LICENSE
Author: Jordan Speicher
Author-email: jordan@jspeicher.com
Requires-Python: >=3.10,<4.0
Classifier: Development Status :: 4 - Beta
Classifier: Framework :: AnyIO
Classifier: Framework :: AsyncIO
Classifier: Framework :: Trio
Classifier: License :: OSI Approved :: MIT License
Classifier: Programming Language :: Python :: 3
Classifier: Programming Language :: Python :: 3.10
Classifier: Programming Language :: Python :: 3.11
Classifier: Programming Language :: Python :: 3.12
Classifier: Programming Language :: Python :: 3.13
Classifier: Programming Language :: Python :: 3.14
Classifier: Topic :: Software Development :: Libraries
Requires-Dist: anyio (>=4,<5)
Requires-Dist: msgpack (>=1,<2)
Project-URL: Repository, https://github.com/uSpike/rpcx
